Workbook

Sheet Dashboard mobile
A53: Série | B53: Inicio | C53: Qtd | D53: Valor | E53: Venc.
A54: ='Simulador Rentabilidade'!A28 -> ATO | B54: ='Simulador Rentabilidade'!B28 -> 45748 | C54: ='Simulador Rentabilidade'!C28 -> 1 | D54: ='Simulador Rentabilidade'!D28 -> 41000 | E54: =Table357[[#This Row],[Valor]] -> 41000
A55: ='Simulador Rentabilidade'!A29 -> SINAL | B55: ='Simulador Rentabilidade'!B29 -> 45778 | C55: ='Simulador Rentabilidade'!C29 -> 3 | D55: ='Simulador Rentabilidade'!D29 -> 6833.3333 | E55: ='Simulador Rentabilidade'!E29 -> 20500
A56: ='Simulador Rentabilidade'!A30 -> MENSAIS | B56: ='Simulador Rentabilidade'!B30 -> 45870 | C56: ='Simulador Rentabilidade'!C30 -> 23 | D56: ='Simulador Rentabilidade'!D30 -> 891.30435 | E56: ='Simulador Rentabilidade'!E30 -> 20500
A57: ='Simulador Rentabilidade'!A31 -> ANUAIS | B57: ='Simulador Rentabilidade'!B31 -> 46113 | C57: ='Simulador Rentabilidade'!C31 -> 2 | D57: ='Simulador Rentabilidade'!D31 -> 10250 | E57: ='Simulador Rentabilidade'!E31 -> 20500
A58: ='Simulador Rentabilidade'!A32 -> ÚNICA | B58: ='Simulador Rentabilidade'!B32 -> 46784 | C58: ='Simulador Rentabilidade'!C32 -> 1 | D58: ='Simulador Rentabilidade'!D32 -> 20500 | E58: ='Simulador Rentabilidade'!E32 -> 20500
A59: ='Simulador Rentabilidade'!A33 -> FINANCIAMENTO | B59: ='Simulador Rentabilidade'!B33 -> 46813 | C59: ='Simulador Rentabilidade'!C33 -> 1 | D59: ='Simulador Rentabilidade'!D33 -> 286590 | E59: ='Simulador Rentabilidade'!E33 -> 286590
A60: ='Simulador Rentabilidade'!A34 -> PERIODICIDADE | B60: ='Simulador Rentabilidade'!B34 -> 46844 | C60: ='Simulador Rentabilidade'!C34 -> 1 | D60: ='Simulador Rentabilidade'!D34 -> 410 | E60: ='Simulador Rentabilidade'!E34 -> 410
D61: ='Simulador Rentabilidade'!D35 -> Total | E61: ='Simulador Rentabilidade'!E35 -> 410000

Sheet Dashboard
A2: 0

Sheet Simulador Rentabilidade
A2: Dados de Entrada
A4: Parâmetro | B4: Valor
A5: Valor do m² (R$) | B5: 32400
A6: Metragem do Studio (m²) | B6: 25
A7: Empreendimento | B7: Vitacon Domingos de Morais | C7: lista
A8: Bairro | B8: =VLOOKUP(B7,Endereços!$A$2:$C$37,3,FALSE) -> Vila Mariana | C8: fórmula
A9: Endereço | B9: =VLOOKUP(B7,Endereços!A:B,2,FALSE) -> Rua Domingos de Morais, 3093 | C9: fórmula
A10: Valor da diária (R$) | B10: =VLOOKUP(B8,'Diária por Bairro'!$A$2:$B$23,2,FALSE) -> 300 | C10: fórmula
A11: Taxa de ocupação (%) | B11: 0.75
A12: Custos operacionais (%) | B12: 0.24
A13: Resultados
A14: Periodo Obra | B14: 123410
A15: Financiamento | B15: 286590
A16: Valor total do imóvel (R$) | B16: 410000 | C16: fórmula
A17: Faturamento bruto mensal (R$) | B17: =B10*(B11*30) -> 6750 | C17: fórmula
A18: Custos operacionais (R$) | B18: =B12*B17 -> 1620 | C18: fórmula
A19: Lucro líquido mensal (R$) | B19: =B17-B18 -> 5130 | C19: fórmula
A20: Expectativa rentabilidade mensal sobre patrimonio (%) | B20: =B19/B16 -> 0.012512195 | C20: fórmula
A21: Expectativa rentabilidade anual sobre patriomonio (%) | B21: 0.16 | C21: fórmula
A22: Expectativa rentabilidade sobre aporte (%) | B22: =B19/B14 -> 0.041568755 | C22: fórmula
A23: Expectativa de rentabilidade anual sobre aporte(%) | B23: =B22*12 -> 0.49882505 | C23: fórmula
A24: Média valorização no periodo de obra | B24: 0.32
A25: Média valor do ativo na Entrega | B25: =B16+(B16*B24) -> 541200
A27: Série | B27: Inicio | C27: Quantidade | D27: Valor | E27: Total | F27: % | G27: % parcela | H27: Tempo | I27: Soma Tempo
A28: ATO | B28: 45748 | C28: 1 | D28: =SUM(E35)*F28 -> 41000 | E28: =SUM(C28)*D28 -> 41000 | F28: 0.1 | G28: =SUM(F28/C28) -> 0.1 | H28: Em Obras
A29: SINAL | B29: 45778 | C29: 3 | D29: =SUM(E35)*F29/C29 -> 6833.3333 | E29: =SUM(C29)*D29 -> 20500 | F29: 0.05 | G29: =SUM(F29/C29) -> 0.016666667 | H29: Em Obras
A30: MENSAIS | B30: 45870 | C30: 23 | D30: =SUM(E35)*F30/C30 -> 891.30435 | E30: =SUM(C30)*D30 -> 20500 | F30: 0.05 | G30: =SUM(F30/C30) -> 0.002173913 | H30: Em Obras
A31: ANUAIS | B31: 46113 | C31: 2 | D31: =SUM(E35)*F31/C31 -> 10250 | E31: =SUM(C31)*D31 -> 20500 | F31: 0.05 | G31: =SUM(F31/C31) -> 0.025 | H31: Em Obras
A32: ÚNICA | B32: 46784 | C32: 1 | D32: =SUM(E35)*F32/C32 -> 20500 | E32: =SUM(C32)*D32 -> 20500 | F32: 0.05 | G32: =SUM(F32/C32) -> 0.05 | H32: Em Obras | I32: =SUM(F28:F32) -> 0.3
A33: FINANCIAMENTO | B33: 46813 | C33: 1 | D33: =SUM(E35)*F33/C33 -> 286590 | E33: =SUM(C33)*D33 -> 286590 | F33: 0.699 | G33: =SUM(F33/C33) -> 0.699 | H33: Financiamento
A34: PERIODICIDADE | B34: 46844 | C34: 1 | D34: =SUM(E35)*F34/C34 -> 410 | E34: =SUM(C34)*D34 -> 410 | F34: 0.001 | G34: =SUM(F34/C34) -> 0.001 | H34: Financiamento | I34: =SUM(G33:G34) -> 0.7
D35: Total | E35: 410000
B39: Valor / m2
B40: M2
B41: Valor da diaria
B42: % taxa de coupacao

Sheet Calculos
A1: Cálculo do Faturamento bruto mensal (R$)
A2: Valor da diária x quantidade dias (referência mês 30 dias)
A3: Dias | B3: Valor Mensal | C3: %
A4: 15 | B4: =A4*'Simulador Rentabilidade'!$B$10-'Simulador Rentabilidade'!$B$18 -> 2880 | C4: 0.5
A5: 18 | B5: =A5*'Simulador Rentabilidade'!$B$10-'Simulador Rentabilidade'!$B$18 -> 3780 | C5: 0.6
A6: 21 | B6: =A6*'Simulador Rentabilidade'!$B$10-'Simulador Rentabilidade'!$B$18 -> 4680 | C6: 0.7
A7: 22.5 | B7: =A7*'Simulador Rentabilidade'!$B$10-'Simulador Rentabilidade'!$B$18 -> 5130 | C7: 0.75
A8: 24 | B8: =A8*'Simulador Rentabilidade'!$B$10-'Simulador Rentabilidade'!$B$18 -> 5580 | C8: 0.8
A9: 27 | B9: =A9*'Simulador Rentabilidade'!$B$10-'Simulador Rentabilidade'!$B$18 -> 6480 | C9: 0.9
A10: 30 | B10: =A10*'Simulador Rentabilidade'!$B$10-'Simulador Rentabilidade'!$B$18 -> 7380 | C10: 1
A13: Cálculo da Estimativa de Valorização em R$
A14: Valor do imóvel * valorização
A16: ='Simulador Rentabilidade'!B16 -> 410000
A17: Data | B17: % Valorização | C17: R$
A18: ='Simulador Rentabilidade'!B28 -> 45748 | B18: 0 | C18: =$A$16+$A$16*B18 -> 410000
A19: 46357 | B19: 0.2 | C19: =$A$16+$A$16*B19 -> 492000
A20: 46722 | B20: 0.4 | C20: =$A$16+$A$16*B20 -> 574000
A21: 47088 | B21: 0.6 | C21: =$A$16+$A$16*B21 -> 656000
A24: Cálculo do Lucro Líquido Mensal
A25: Faturamento Bruto - Custos Operacionais
A26: Detalhe | B26: Bruto | C26: Liquido | D26: Custos
A27: Faturamento | B27: ='Simulador Rentabilidade'!B17 -> 6750 | C27: ='Simulador Rentabilidade'!B19 -> 5130 | D27: ='Simulador Rentabilidade'!B18 -> 1620

Sheet Endereços
A1: Empreendimento | B1: Endereço | C1: Bairro
A2: Vitacon Casa Verde | B2: Avenida Casa Verde, 3482 | C2: Casa Verde
A3: Vitacon Alameda Franca | B3: Alameda Franca, 253 | C3: Jardins
A4: Vitacon Jardins | B4: Rua Augusta, 2662 | C4: Jardins
A5: Vitacon Pinheiros | B5: Rua Heitor Penteado,177 | C5: Pinheiros
A6: Vitacon Domingos de Morais | B6: Rua Domingos de Morais, 3093 | C6: Vila Mariana
A7: Vitacon Perdizes | B7: Rua Padre Chico, 183 | C7: Perdizes
A8: H Bela Cintra By Vitacon | B8: Rua Bela Cintra, 1425 | C8: Jardins
A9: Vitacon Mourato Coelho | B9: Rua Mourato Coelho, 128 | C9: Pinheiros
A10: Vitacon Maestro Cardim | B10: Rua Maestro Cardim, 1041 | C10: Paraíso
A11: Vitacon Vila Olímpia | B11: Rua Alvorada, 203 | C11: Vila Olímpia
A12: Vitacon Alto de Pinheiros | B12: Rua Tonelero, 1213 | C12: Alto de Pinheiros
... A37: VN Consolação | B37: Rua da Consolação, 297 | C37: Bela Vista

Sheet Diária por Bairro
A1: Bairro | B1: Valor Diária
A2: Casa Verde | B2: 250
A3: Jardins | B3: 380
A4: Pinheiros | B4: 380
A5: Vila Mariana | B5: 300
A6: Perdizes | B6: 450
A7: Paraíso | B7: 350
A8: Vila Olímpia | B8: 300
A9: Alto de Pinheiros | B9: 300
A10: Bela Vista | B10: 350
A11: Itaim Bibi | B11: 350
A12: Alto da Boa Vista | B12: =B11-10 -> 340
A13: Brooklin | B13: 395
A14: Consolação | B14: =B13-10 -> 385
A15: Moema | B15: 300
A16: Ipiranga | B16: =B15-10 -> 290
A17: Higienópolis | B17: =B16-10 -> 280
A18: Bom Retiro | B18: =B17-10 -> 270
A19: Aclimação | B19: =B18-10 -> 260
A20: Pompéia | B20: =B19-10 -> 250
A21: Saúde | B21: =B20-10 -> 240
A22: Morumbi | B22: =B21-10 -> 230
A23: Sumaré | B23: =B22-10 -> 220
